elemental_agents/__init__.py
elemental_agents/core/__init__.py
elemental_agents/core/agent/__init__.py
elemental_agents/core/agent/agent.py
elemental_agents/core/agent/agent_factory.py
elemental_agents/core/agent/generic_agent.py
elemental_agents/core/agent/generic_agent_with_context.py
elemental_agents/core/agent/simple_agent.py
elemental_agents/core/agent_logic/__init__.py
elemental_agents/core/agent_logic/agent_logic.py
elemental_agents/core/agent_logic/agent_logic_factory.py
elemental_agents/core/agent_logic/agent_model.py
elemental_agents/core/agent_logic/composer_agent.py
elemental_agents/core/agent_logic/conv_planreact_agent.py
elemental_agents/core/agent_logic/generic_agent.py
elemental_agents/core/agent_logic/plan_verifier_agent.py
elemental_agents/core/agent_logic/planner_agent.py
elemental_agents/core/agent_logic/planreact_agent.py
elemental_agents/core/agent_logic/react_agent.py
elemental_agents/core/agent_logic/replanner_agent.py
elemental_agents/core/agent_logic/simple_agent.py
elemental_agents/core/agent_logic/verifier_agent.py
elemental_agents/core/agent_team/__init__.py
elemental_agents/core/agent_team/agent_team.py
elemental_agents/core/agent_team/generic_agent_team.py
elemental_agents/core/context/__init__.py
elemental_agents/core/context/context_manager.py
elemental_agents/core/context/integration.py
elemental_agents/core/driver/__init__.py
elemental_agents/core/driver/driver.py
elemental_agents/core/driver/workflow_config.py
elemental_agents/core/instruction/__init__.py
elemental_agents/core/instruction/instruction.py
elemental_agents/core/memory/__init__.py
elemental_agents/core/memory/long_memory.py
elemental_agents/core/memory/memory.py
elemental_agents/core/memory/short_memory.py
elemental_agents/core/orchestration/__init__.py
elemental_agents/core/orchestration/dynamic_agent_orchestrator.py
elemental_agents/core/orchestration/orchestrator.py
elemental_agents/core/prompt_strategy/__init__.py
elemental_agents-0.1.7.dist-info/LICENSE.md
elemental_agents-0.1.7.dist-info/METADATA
elemental_agents-0.1.7.dist-info/WHEEL
elemental_agents-0.1.7.dist-info/RECORD
