Metadata-Version: 2.3
Name: elemental-agents
Version: 0.1.7
Summary: Multi-agent Framework for conversational collaborative AI agents for task automation.
License: MIT
Keywords: python,AI,agents,multi-agent,conversational,automation,task,collaborative,framework
Author: Marcin Ziolkowski
Author-email: mz@attoagents.io
Maintainer: Marcin Ziolkowski
Maintainer-email: mz@attoagents.io
Requires-Python: >=3.12
Classifier: Development Status :: 3 - Alpha
Classifier: Intended Audience :: Developers
Classifier: Intended Audience :: Science/Research
Classifier: License :: OSI Approved :: MIT License
Classifier: Operating System :: OS Independent
Classifier: Programming Language :: Python :: 3
Classifier: Programming Language :: Python :: 3.12
Classifier: Programming Language :: Python :: 3.13
Classifier: Topic :: Scientific/Engineering :: Artificial Intelligence
Classifier: Topic :: Scientific/Engineering :: Human Machine Interfaces
Requires-Dist: Jinja2 (>=3.1.6)
Requires-Dist: PyYAML (>=6.0.1)
Requires-Dist: SQLAlchemy (>=2.0.29)
Requires-Dist: aiohttp (>=3.11.12)
Requires-Dist: anthropic (>=0.58.2)
Requires-Dist: beautifulsoup4 (>=4.13.4)
Requires-Dist: boto3 (>=1.38.40)
Requires-Dist: chromadb (>=1.0.15)
Requires-Dist: click (>=8.1.7)
Requires-Dist: docker (>=7.1.0)
Requires-Dist: google-api-python-client (>=2.146.0)
Requires-Dist: google-genai (>=1.26.0)
Requires-Dist: loguru (>=0.7.2)
Requires-Dist: markitdown[docx,pdf,pptx,xlsx] (>=0.1.1)
Requires-Dist: mcp (>=1.12.1)
Requires-Dist: ollama (>=0.5.1)
Requires-Dist: openai (>=1.97.1)
Requires-Dist: pgvector (>=0.4.1)
Requires-Dist: pydantic (>=2.11.7)
Requires-Dist: pydantic-settings (>=2.5.2)
Requires-Dist: python-docx (>=1.1.2)
Requires-Dist: python-socketio (>=5.12.1)
Requires-Dist: requests (>=2.31.0)
Requires-Dist: rich (>=13.7.1)
Requires-Dist: urllib3 (>=2.3.0)
Requires-Dist: wikipedia-api (>=0.7.1)
Project-URL: Documentation, https://attoagents.io/elemental/documentation
Project-URL: Homepage, https://attoagents.io/elemental
Project-URL: Repository, https://github.com/AttoAgents/elemental.git
Project-URL: issues, https://github.com/AttoAgents/elemental/issues
